{
  "sample_id": "sample_3415",
  "generation_timestamp": "2025-08-04T18:30:58.796754",
  "generator_version": "v1.0",
  "batch_id": "batch_035",
  "classification": {
    "document_type": "INFLUENCER_AGREEMENT",
    "confidence_target": 0.85,
    "complexity_level": "complex",
    "industry": "fashion",
    "should_process": true
  },
  "raw_input": {
    "text": "Hey team, looking to work with Sage Reed for Country Road. \n            Budget is approx $34,487 - need 1 x Instagram post, 1 x 3-minute vlog, 1 x Press conference, 1 x Pinterest pin. \n            11 weeks exclusivity, 3 month engagement. \n            Usage: 8 months. Start date: October 2025.",
    "token_count": 73,
    "requires_chunking": false,
    "text_style": "casual",
    "completeness": "complete"
  },
  "extracted_fields": {
    "influencer": "Sage Reed",
    "client": "Country Road",
    "brand": "Country Road",
    "campaign": "Country Road Campaign",
    "fee": "$34,487",
    "fee_numeric": 34487,
    "deliverables": [
      "1 x Instagram post",
      "1 x 3-minute vlog",
      "1 x Press conference",
      "1 x Pinterest pin"
    ],
    "exclusivity_period": "11 weeks",
    "exclusivity_scope": "fashion",
    "engagement_term": "3 months",
    "usage_term": "8 months",
    "territory": "Australia",
    "start_date": "October 2025"
  },
  "template_mapping": {
    "best_template_match": "template_style_4",
    "match_confidence": 0.5,
    "fallback_templates": [
      "template_03",
      "template_04"
    ]
  },
  "validation_scores": {
    "semantic_coherence": 0.6877087668228914,
    "business_logic_valid": true,
    "temporal_logic_valid": true,
    "field_extractability": 0.7679934585592849,
    "human_reviewed": false
  },
  "generation_metadata": {
    "base_template_used": "template_style_4",
    "variation_strategy": "parameter_substitution",
    "semantic_smoother_passes": 1,
    "ood_contamination": false
  },
  "metadata": {
    "generated_at": "2025-08-04T18:30:58.788754",
    "fee_tier": "premium",
    "num_deliverables": 4,
    "campaign_type": "Seasonal Promotion",
    "product_category": "Health & Fitness"
  }
}