{
  "sample_id": "sample_2049",
  "generation_timestamp": "2025-08-04T18:30:29.309449",
  "generator_version": "v1.0",
  "batch_id": "batch_021",
  "classification": {
    "document_type": "INFLUENCER_AGREEMENT",
    "confidence_target": 0.85,
    "complexity_level": "simple",
    "industry": "other",
    "should_process": true
  },
  "raw_input": {
    "text": "• Influencer: Blake Morgan\n            • Brand: Betty's Burgers\n            • Fee: ~$5,648\n            • Deliverables: 3 x Article contribution, 2 x Facebook post\n            • Exclusivity: 12 weeks\n            • Engagement: 3 months\n            • Usage: 8 months\n            • Start: November 2025",
    "token_count": 74,
    "requires_chunking": false,
    "text_style": "bullet_points",
    "completeness": "complete"
  },
  "extracted_fields": {
    "influencer": "Blake Morgan",
    "client": "Betty's Burgers",
    "brand": "Betty's Burgers",
    "campaign": "Betty's Burgers Campaign",
    "fee": "$5,648",
    "fee_numeric": 5648,
    "deliverables": [
      "3 x Article contribution",
      "2 x Facebook post"
    ],
    "exclusivity_period": "12 weeks",
    "exclusivity_scope": "similar",
    "engagement_term": "3 months",
    "usage_term": "8 months",
    "territory": "Australia",
    "start_date": "November 2025"
  },
  "template_mapping": {
    "best_template_match": "template_style_1",
    "match_confidence": 0.9,
    "fallback_templates": [
      "template_01",
      "template_02"
    ]
  },
  "validation_scores": {
    "semantic_coherence": 0.7513869171461687,
    "business_logic_valid": true,
    "temporal_logic_valid": true,
    "field_extractability": 0.9270246063618359,
    "human_reviewed": false
  },
  "generation_metadata": {
    "base_template_used": "template_style_1",
    "variation_strategy": "parameter_substitution",
    "semantic_smoother_passes": 1,
    "ood_contamination": false
  },
  "metadata": {
    "generated_at": "2025-08-04T18:30:29.291448",
    "fee_tier": "mid",
    "num_deliverables": 2,
    "campaign_type": "Collaboration",
    "product_category": "Automotive"
  }
}