{
  "sample_id": "sample_1343",
  "generation_timestamp": "2025-08-04T18:30:13.205742",
  "generator_version": "v1.0",
  "batch_id": "batch_014",
  "classification": {
    "document_type": "INFLUENCER_AGREEMENT",
    "confidence_target": 0.85,
    "complexity_level": "simple",
    "industry": "other",
    "should_process": true
  },
  "raw_input": {
    "text": "Emma Thompson for Betty's Burgers - $27,733 budget\n            Need: 1 x Instagram post\n            6w exclusivity, 4m engagement\n            Usage rights: 10 months\n            Start: January 2026",
    "token_count": 49,
    "requires_chunking": false,
    "text_style": "casual",
    "completeness": "complete"
  },
  "extracted_fields": {
    "influencer": "Emma Thompson",
    "client": "Betty's Burgers",
    "brand": "Betty's Burgers",
    "campaign": "Betty's Burgers Campaign",
    "fee": "$27,733",
    "fee_numeric": 27733,
    "deliverables": [
      "1 x Instagram post"
    ],
    "exclusivity_period": "6 weeks",
    "exclusivity_scope": "similar",
    "engagement_term": "4 months",
    "usage_term": "10 months",
    "territory": "Australia",
    "start_date": "January 2026"
  },
  "template_mapping": {
    "best_template_match": "template_style_1",
    "match_confidence": 0.9,
    "fallback_templates": [
      "template_01",
      "template_02"
    ]
  },
  "validation_scores": {
    "semantic_coherence": 0.9286579402053088,
    "business_logic_valid": true,
    "temporal_logic_valid": true,
    "field_extractability": 0.9303480557995849,
    "human_reviewed": false
  },
  "generation_metadata": {
    "base_template_used": "template_style_1",
    "variation_strategy": "parameter_substitution",
    "semantic_smoother_passes": 1,
    "ood_contamination": false
  },
  "metadata": {
    "generated_at": "2025-08-04T18:30:13.197744",
    "fee_tier": "premium",
    "num_deliverables": 1,
    "campaign_type": "Accessories Launch",
    "product_category": "Technology & Electronics"
  }
}