{
  "batch_id": "batch_016",
  "generation_start": "2025-08-04T18:30:16.876243",
  "target_size": 100,
  "samples_generated": [
    {
      "sample_id": "sample_1501",
      "filename": "sample_1501_complex_food_inf.json",
      "classification": "INFLUENCER_AGREEMENT",
      "complexity": "complex",
      "industry": "food"
    },
    {
      "sample_id": "sample_1502",
      "filename": "sample_1502_complex_other_inf.json",
      "classification": "INFLUENCER_AGREEMENT",
      "complexity": "complex",
      "industry": "other"
    },
    {
      "sample_id": "sample_1503",
      "filename": "sample_1503_complex_tech_inf.json",
      "classification": "INFLUENCER_AGREEMENT",
      "complexity": "complex",
      "industry": "tech"
    },
    {
      "sample_id": "sample_1504",
      "filename": "sample_1504_simple_beauty_inf.json",
      "classification": "INFLUENCER_AGREEMENT",
      "complexity": "simple",
      "industry": "beauty"
    },
    {
      "sample_id": "sample_1505",
      "filename": "sample_1505_complex_other_inf.json",
      "classification": "INFLUENCER_AGREEMENT",
      "complexity": "complex",
      "industry": "other"
    },
    {
      "sample_id": "sample_1506",
      "filename": "sample_1506_medium_food_inf.json",
      "classification": "INFLUENCER_AGREEMENT",
      "complexity": "medium",
      "industry": "food"
    },
    {
      "sample_id": "sample_1507",
      "filename": "sample_1507_simple_food_inf.json",
      "classification": "INFLUENCER_AGREEMENT",
      "complexity": "simple",
      "industry": "food"
    },
    {
      "sample_id": "sample_1508",
      "filename": "sample_1508_medium_other_inf.json",
      "classification": "INFLUENCER_AGREEMENT",
      "complexity": "medium",
      "industry": "other"
    },
    {
      "sample_id": "sample_1509",
      "filename": "sample_1509_simple_other_inf.json",
      "classification": "INFLUENCER_AGREEMENT",
      "complexity": "simple",
      "industry": "other"
    },
    {
      "sample_id": "sample_1510",
      "filename": "sample_1510_medium_automotive_inf.json",
      "classification": "INFLUENCER_AGREEMENT",
      "complexity": "medium",
      "industry": "automotive"
    },
    {
      "sample_id": "sample_1511",
      "filename": "sample_1511_simple_automotive_inf.json",
      "classification": "INFLUENCER_AGREEMENT",
      "complexity": "simple",
      "industry": "automotive"
    },
    {
      "sample_id": "sample_1512",
      "filename": "sample_1512_medium_home_inf.json",
      "classification": "INFLUENCER_AGREEMENT",
      "complexity": "medium",
      "industry": "home"
    },
    {
      "sample_id": "sample_1513",
      "filename": "sample_1513_complex_other_inf.json",
      "classification": "INFLUENCER_AGREEMENT",
      "complexity": "complex",
      "industry": "other"
    },
    {
      "sample_id": "sample_1514",
      "filename": "sample_1514_medium_fashion_inf.json",
      "classification": "INFLUENCER_AGREEMENT",
      "complexity": "medium",
      "industry": "fashion"
    },
    {
      "sample_id": "sample_1515",
      "filename": "sample_1515_medium_food_inf.json",
      "classification": "INFLUENCER_AGREEMENT",
      "complexity": "medium",
      "industry": "food"
    },
    {
      "sample_id": "sample_1516",
      "filename": "sample_1516_complex_other_inf.json",
      "classification": "INFLUENCER_AGREEMENT",
      "complexity": "complex",
      "industry": "other"
    },
    {
      "sample_id": "sample_1517",
      "filename": "sample_1517_simple_other_inf.json",
      "classification": "INFLUENCER_AGREEMENT",
      "complexity": "simple",
      "industry": "other"
    },
    {
      "sample_id": "sample_1518",
      "filename": "sample_1518_complex_beauty_inf.json",
      "classification": "INFLUENCER_AGREEMENT",
      "complexity": "complex",
      "industry": "beauty"
    },
    {
      "sample_id": "sample_1519",
      "filename": "sample_1519_complex_beauty_inf.json",
      "classification": "INFLUENCER_AGREEMENT",
      "complexity": "complex",
      "industry": "beauty"
    },
    {
      "sample_id": "sample_1520",
      "filename": "sample_1520_simple_beauty_inf.json",
      "classification": "INFLUENCER_AGREEMENT",
      "complexity": "simple",
      "industry": "beauty"
    },
    {
      "sample_id": "sample_1521",
      "filename": "sample_1521_medium_automotive_inf.json",
      "classification": "INFLUENCER_AGREEMENT",
      "complexity": "medium",
      "industry": "automotive"
    },
    {
      "sample_id": "sample_1522",
      "filename": "sample_1522_simple_tech_inf.json",
      "classification": "INFLUENCER_AGREEMENT",
      "complexity": "simple",
      "industry": "tech"
    },
    {
      "sample_id": "sample_1523",
      "filename": "sample_1523_medium_beauty_inf.json",
      "classification": "INFLUENCER_AGREEMENT",
      "complexity": "medium",
      "industry": "beauty"
    },
    {
      "sample_id": "sample_1524",
      "filename": "sample_1524_medium_other_inf.json",
      "classification": "INFLUENCER_AGREEMENT",
      "complexity": "medium",
      "industry": "other"
    },
    {
      "sample_id": "sample_1525",
      "filename": "sample_1525_simple_other_inf.json",
      "classification": "INFLUENCER_AGREEMENT",
      "complexity": "simple",
      "industry": "other"
    },
    {
      "sample_id": "sample_1526",
      "filename": "sample_1526_complex_beauty_inf.json",
      "classification": "INFLUENCER_AGREEMENT",
      "complexity": "complex",
      "industry": "beauty"
    },
    {
      "sample_id": "sample_1527",
      "filename": "sample_1527_complex_other_inf.json",
      "classification": "INFLUENCER_AGREEMENT",
      "complexity": "complex",
      "industry": "other"
    },
    {
      "sample_id": "sample_1528",
      "filename": "sample_1528_medium_food_inf.json",
      "classification": "INFLUENCER_AGREEMENT",
      "complexity": "medium",
      "industry": "food"
    },
    {
      "sample_id": "sample_1529",
      "filename": "sample_1529_simple_food_inf.json",
      "classification": "INFLUENCER_AGREEMENT",
      "complexity": "simple",
      "industry": "food"
    },
    {
      "sample_id": "sample_1530",
      "filename": "sample_1530_simple_other_inf.json",
      "classification": "INFLUENCER_AGREEMENT",
      "complexity": "simple",
      "industry": "other"
    },
    {
      "sample_id": "sample_1531",
      "filename": "sample_1531_complex_beauty_inf.json",
      "classification": "INFLUENCER_AGREEMENT",
      "complexity": "complex",
      "industry": "beauty"
    },
    {
      "sample_id": "sample_1532",
      "filename": "sample_1532_medium_other_inf.json",
      "classification": "INFLUENCER_AGREEMENT",
      "complexity": "medium",
      "industry": "other"
    },
    {
      "sample_id": "sample_1533",
      "filename": "sample_1533_simple_tech_inf.json",
      "classification": "INFLUENCER_AGREEMENT",
      "complexity": "simple",
      "industry": "tech"
    },
    {
      "sample_id": "sample_1534",
      "filename": "sample_1534_simple_other_inf.json",
      "classification": "INFLUENCER_AGREEMENT",
      "complexity": "simple",
      "industry": "other"
    },
    {
      "sample_id": "sample_1535",
      "filename": "sample_1535_simple_home_inf.json",
      "classification": "INFLUENCER_AGREEMENT",
      "complexity": "simple",
      "industry": "home"
    },
    {
      "sample_id": "sample_1536",
      "filename": "sample_1536_simple_fashion_inf.json",
      "classification": "INFLUENCER_AGREEMENT",
      "complexity": "simple",
      "industry": "fashion"
    },
    {
      "sample_id": "sample_1537",
      "filename": "sample_1537_simple_beauty_inf.json",
      "classification": "INFLUENCER_AGREEMENT",
      "complexity": "simple",
      "industry": "beauty"
    },
    {
      "sample_id": "sample_1538",
      "filename": "sample_1538_simple_home_inf.json",
      "classification": "INFLUENCER_AGREEMENT",
      "complexity": "simple",
      "industry": "home"
    },
    {
      "sample_id": "sample_1539",
      "filename": "sample_1539_medium_other_inf.json",
      "classification": "INFLUENCER_AGREEMENT",
      "complexity": "medium",
      "industry": "other"
    },
    {
      "sample_id": "sample_1540",
      "filename": "sample_1540_simple_fashion_inf.json",
      "classification": "INFLUENCER_AGREEMENT",
      "complexity": "simple",
      "industry": "fashion"
    },
    {
      "sample_id": "sample_1541",
      "filename": "sample_1541_medium_other_inf.json",
      "classification": "INFLUENCER_AGREEMENT",
      "complexity": "medium",
      "industry": "other"
    },
    {
      "sample_id": "sample_1542",
      "filename": "sample_1542_simple_other_inf.json",
      "classification": "INFLUENCER_AGREEMENT",
      "complexity": "simple",
      "industry": "other"
    },
    {
      "sample_id": "sample_1543",
      "filename": "sample_1543_medium_tech_inf.json",
      "classification": "INFLUENCER_AGREEMENT",
      "complexity": "medium",
      "industry": "tech"
    },
    {
      "sample_id": "sample_1544",
      "filename": "sample_1544_simple_other_inf.json",
      "classification": "INFLUENCER_AGREEMENT",
      "complexity": "simple",
      "industry": "other"
    },
    {
      "sample_id": "sample_1545",
      "filename": "sample_1545_simple_other_inf.json",
      "classification": "INFLUENCER_AGREEMENT",
      "complexity": "simple",
      "industry": "other"
    },
    {
      "sample_id": "sample_1546",
      "filename": "sample_1546_simple_home_inf.json",
      "classification": "INFLUENCER_AGREEMENT",
      "complexity": "simple",
      "industry": "home"
    },
    {
      "sample_id": "sample_1547",
      "filename": "sample_1547_medium_other_inf.json",
      "classification": "INFLUENCER_AGREEMENT",
      "complexity": "medium",
      "industry": "other"
    },
    {
      "sample_id": "sample_1548",
      "filename": "sample_1548_complex_food_inf.json",
      "classification": "INFLUENCER_AGREEMENT",
      "complexity": "complex",
      "industry": "food"
    },
    {
      "sample_id": "sample_1549",
      "filename": "sample_1549_simple_other_inf.json",
      "classification": "INFLUENCER_AGREEMENT",
      "complexity": "simple",
      "industry": "other"
    },
    {
      "sample_id": "sample_1550",
      "filename": "sample_1550_complex_food_inf.json",
      "classification": "INFLUENCER_AGREEMENT",
      "complexity": "complex",
      "industry": "food"
    },
    {
      "sample_id": "sample_1551",
      "filename": "sample_1551_simple_fashion_inf.json",
      "classification": "INFLUENCER_AGREEMENT",
      "complexity": "simple",
      "industry": "fashion"
    },
    {
      "sample_id": "sample_1552",
      "filename": "sample_1552_simple_fashion_inf.json",
      "classification": "INFLUENCER_AGREEMENT",
      "complexity": "simple",
      "industry": "fashion"
    },
    {
      "sample_id": "sample_1553",
      "filename": "sample_1553_complex_automotive_inf.json",
      "classification": "INFLUENCER_AGREEMENT",
      "complexity": "complex",
      "industry": "automotive"
    },
    {
      "sample_id": "sample_1554",
      "filename": "sample_1554_medium_automotive_inf.json",
      "classification": "INFLUENCER_AGREEMENT",
      "complexity": "medium",
      "industry": "automotive"
    },
    {
      "sample_id": "sample_1555",
      "filename": "sample_1555_simple_food_inf.json",
      "classification": "INFLUENCER_AGREEMENT",
      "complexity": "simple",
      "industry": "food"
    },
    {
      "sample_id": "sample_1556",
      "filename": "sample_1556_complex_tech_inf.json",
      "classification": "INFLUENCER_AGREEMENT",
      "complexity": "complex",
      "industry": "tech"
    },
    {
      "sample_id": "sample_1557",
      "filename": "sample_1557_simple_other_inf.json",
      "classification": "INFLUENCER_AGREEMENT",
      "complexity": "simple",
      "industry": "other"
    },
    {
      "sample_id": "sample_1558",
      "filename": "sample_1558_medium_other_inf.json",
      "classification": "INFLUENCER_AGREEMENT",
      "complexity": "medium",
      "industry": "other"
    },
    {
      "sample_id": "sample_1559",
      "filename": "sample_1559_simple_other_inf.json",
      "classification": "INFLUENCER_AGREEMENT",
      "complexity": "simple",
      "industry": "other"
    },
    {
      "sample_id": "sample_1560",
      "filename": "sample_1560_medium_home_inf.json",
      "classification": "INFLUENCER_AGREEMENT",
      "complexity": "medium",
      "industry": "home"
    },
    {
      "sample_id": "sample_1561",
      "filename": "sample_1561_medium_other_inf.json",
      "classification": "INFLUENCER_AGREEMENT",
      "complexity": "medium",
      "industry": "other"
    },
    {
      "sample_id": "sample_1562",
      "filename": "sample_1562_complex_other_inf.json",
      "classification": "INFLUENCER_AGREEMENT",
      "complexity": "complex",
      "industry": "other"
    },
    {
      "sample_id": "sample_1563",
      "filename": "sample_1563_medium_fashion_inf.json",
      "classification": "INFLUENCER_AGREEMENT",
      "complexity": "medium",
      "industry": "fashion"
    },
    {
      "sample_id": "sample_1564",
      "filename": "sample_1564_complex_beauty_inf.json",
      "classification": "INFLUENCER_AGREEMENT",
      "complexity": "complex",
      "industry": "beauty"
    },
    {
      "sample_id": "sample_1565",
      "filename": "sample_1565_simple_beauty_inf.json",
      "classification": "INFLUENCER_AGREEMENT",
      "complexity": "simple",
      "industry": "beauty"
    },
    {
      "sample_id": "sample_1566",
      "filename": "sample_1566_medium_fashion_inf.json",
      "classification": "INFLUENCER_AGREEMENT",
      "complexity": "medium",
      "industry": "fashion"
    },
    {
      "sample_id": "sample_1567",
      "filename": "sample_1567_medium_fashion_inf.json",
      "classification": "INFLUENCER_AGREEMENT",
      "complexity": "medium",
      "industry": "fashion"
    },
    {
      "sample_id": "sample_1568",
      "filename": "sample_1568_complex_home_inf.json",
      "classification": "INFLUENCER_AGREEMENT",
      "complexity": "complex",
      "industry": "home"
    },
    {
      "sample_id": "sample_1569",
      "filename": "sample_1569_simple_other_inf.json",
      "classification": "INFLUENCER_AGREEMENT",
      "complexity": "simple",
      "industry": "other"
    },
    {
      "sample_id": "sample_1570",
      "filename": "sample_1570_simple_fashion_inf.json",
      "classification": "INFLUENCER_AGREEMENT",
      "complexity": "simple",
      "industry": "fashion"
    },
    {
      "sample_id": "sample_1571",
      "filename": "sample_1571_medium_food_inf.json",
      "classification": "INFLUENCER_AGREEMENT",
      "complexity": "medium",
      "industry": "food"
    },
    {
      "sample_id": "sample_1572",
      "filename": "sample_1572_complex_beauty_inf.json",
      "classification": "INFLUENCER_AGREEMENT",
      "complexity": "complex",
      "industry": "beauty"
    },
    {
      "sample_id": "sample_1573",
      "filename": "sample_1573_simple_food_inf.json",
      "classification": "INFLUENCER_AGREEMENT",
      "complexity": "simple",
      "industry": "food"
    },
    {
      "sample_id": "sample_1574",
      "filename": "sample_1574_simple_other_inf.json",
      "classification": "INFLUENCER_AGREEMENT",
      "complexity": "simple",
      "industry": "other"
    },
    {
      "sample_id": "sample_1575",
      "filename": "sample_1575_complex_tech_inf.json",
      "classification": "INFLUENCER_AGREEMENT",
      "complexity": "complex",
      "industry": "tech"
    },
    {
      "sample_id": "sample_1576",
      "filename": "sample_1576_simple_automotive_inf.json",
      "classification": "INFLUENCER_AGREEMENT",
      "complexity": "simple",
      "industry": "automotive"
    },
    {
      "sample_id": "sample_1577",
      "filename": "sample_1577_simple_food_inf.json",
      "classification": "INFLUENCER_AGREEMENT",
      "complexity": "simple",
      "industry": "food"
    },
    {
      "sample_id": "sample_1578",
      "filename": "sample_1578_complex_other_inf.json",
      "classification": "INFLUENCER_AGREEMENT",
      "complexity": "complex",
      "industry": "other"
    },
    {
      "sample_id": "sample_1579",
      "filename": "sample_1579_medium_food_inf.json",
      "classification": "INFLUENCER_AGREEMENT",
      "complexity": "medium",
      "industry": "food"
    },
    {
      "sample_id": "sample_1580",
      "filename": "sample_1580_simple_other_inf.json",
      "classification": "INFLUENCER_AGREEMENT",
      "complexity": "simple",
      "industry": "other"
    },
    {
      "sample_id": "sample_1581",
      "filename": "sample_1581_medium_home_inf.json",
      "classification": "INFLUENCER_AGREEMENT",
      "complexity": "medium",
      "industry": "home"
    },
    {
      "sample_id": "sample_1582",
      "filename": "sample_1582_simple_food_inf.json",
      "classification": "INFLUENCER_AGREEMENT",
      "complexity": "simple",
      "industry": "food"
    },
    {
      "sample_id": "sample_1583",
      "filename": "sample_1583_medium_other_inf.json",
      "classification": "INFLUENCER_AGREEMENT",
      "complexity": "medium",
      "industry": "other"
    },
    {
      "sample_id": "sample_1584",
      "filename": "sample_1584_simple_home_inf.json",
      "classification": "INFLUENCER_AGREEMENT",
      "complexity": "simple",
      "industry": "home"
    },
    {
      "sample_id": "sample_1585",
      "filename": "sample_1585_simple_home_inf.json",
      "classification": "INFLUENCER_AGREEMENT",
      "complexity": "simple",
      "industry": "home"
    },
    {
      "sample_id": "sample_1586",
      "filename": "sample_1586_medium_food_inf.json",
      "classification": "INFLUENCER_AGREEMENT",
      "complexity": "medium",
      "industry": "food"
    },
    {
      "sample_id": "sample_1587",
      "filename": "sample_1587_medium_other_inf.json",
      "classification": "INFLUENCER_AGREEMENT",
      "complexity": "medium",
      "industry": "other"
    },
    {
      "sample_id": "sample_1588",
      "filename": "sample_1588_simple_automotive_inf.json",
      "classification": "INFLUENCER_AGREEMENT",
      "complexity": "simple",
      "industry": "automotive"
    },
    {
      "sample_id": "sample_1589",
      "filename": "sample_1589_medium_beauty_inf.json",
      "classification": "INFLUENCER_AGREEMENT",
      "complexity": "medium",
      "industry": "beauty"
    },
    {
      "sample_id": "sample_1590",
      "filename": "sample_1590_medium_beauty_inf.json",
      "classification": "INFLUENCER_AGREEMENT",
      "complexity": "medium",
      "industry": "beauty"
    },
    {
      "sample_id": "sample_1591",
      "filename": "sample_1591_simple_beauty_inf.json",
      "classification": "INFLUENCER_AGREEMENT",
      "complexity": "simple",
      "industry": "beauty"
    },
    {
      "sample_id": "sample_1592",
      "filename": "sample_1592_medium_tech_inf.json",
      "classification": "INFLUENCER_AGREEMENT",
      "complexity": "medium",
      "industry": "tech"
    },
    {
      "sample_id": "sample_1593",
      "filename": "sample_1593_complex_home_inf.json",
      "classification": "INFLUENCER_AGREEMENT",
      "complexity": "complex",
      "industry": "home"
    },
    {
      "sample_id": "sample_1594",
      "filename": "sample_1594_simple_other_inf.json",
      "classification": "INFLUENCER_AGREEMENT",
      "complexity": "simple",
      "industry": "other"
    },
    {
      "sample_id": "sample_1595",
      "filename": "sample_1595_simple_automotive_inf.json",
      "classification": "INFLUENCER_AGREEMENT",
      "complexity": "simple",
      "industry": "automotive"
    },
    {
      "sample_id": "sample_1596",
      "filename": "sample_1596_simple_other_inf.json",
      "classification": "INFLUENCER_AGREEMENT",
      "complexity": "simple",
      "industry": "other"
    },
    {
      "sample_id": "sample_1597",
      "filename": "sample_1597_simple_automotive_inf.json",
      "classification": "INFLUENCER_AGREEMENT",
      "complexity": "simple",
      "industry": "automotive"
    },
    {
      "sample_id": "sample_1598",
      "filename": "sample_1598_simple_fashion_inf.json",
      "classification": "INFLUENCER_AGREEMENT",
      "complexity": "simple",
      "industry": "fashion"
    },
    {
      "sample_id": "sample_1599",
      "filename": "sample_1599_medium_tech_inf.json",
      "classification": "INFLUENCER_AGREEMENT",
      "complexity": "medium",
      "industry": "tech"
    },
    {
      "sample_id": "sample_1600",
      "filename": "sample_1600_complex_home_inf.json",
      "classification": "INFLUENCER_AGREEMENT",
      "complexity": "complex",
      "industry": "home"
    }
  ],
  "generation_end": "2025-08-04T18:30:18.194687",
  "quality_metrics": {
    "total_samples": 100,
    "classification_distribution": {
      "INFLUENCER_AGREEMENT": 100
    },
    "complexity_distribution": {
      "complex": 23,
      "simple": 45,
      "medium": 32
    },
    "industry_distribution": {
      "food": 15,
      "other": 33,
      "tech": 8,
      "beauty": 14,
      "automotive": 9,
      "home": 11,
      "fashion": 10
    },
    "average_validation_score": 0.8131113055548821
  }
}