{
  "sample_id": "sample_4105",
  "generation_timestamp": "2025-08-04T18:31:13.621293",
  "generator_version": "v1.0",
  "batch_id": "batch_042",
  "classification": {
    "document_type": "INFLUENCER_AGREEMENT",
    "confidence_target": 0.85,
    "complexity_level": "simple",
    "industry": "beauty",
    "should_process": true
  },
  "raw_input": {
    "text": "Jordan Phillips for Priceline - $10,948 budget\n            Need: 2 x Twitter post\n            10w exclusivity, 6m engagement\n            Usage rights: 6 months\n            Start: December 2025",
    "token_count": 48,
    "requires_chunking": false,
    "text_style": "casual",
    "completeness": "complete"
  },
  "extracted_fields": {
    "influencer": "Jordan Phillips",
    "client": "Priceline",
    "brand": "Priceline",
    "campaign": "Priceline Campaign",
    "fee": "$10,948",
    "fee_numeric": 10948,
    "deliverables": [
      "2 x Twitter post"
    ],
    "exclusivity_period": "10 weeks",
    "exclusivity_scope": "similar",
    "engagement_term": "6 months",
    "usage_term": "6 months",
    "territory": "Australia",
    "start_date": "December 2025"
  },
  "template_mapping": {
    "best_template_match": "template_style_2",
    "match_confidence": 0.9,
    "fallback_templates": [
      "template_01",
      "template_02"
    ]
  },
  "validation_scores": {
    "semantic_coherence": 0.7762753604418058,
    "business_logic_valid": true,
    "temporal_logic_valid": true,
    "field_extractability": 0.863149403764326,
    "human_reviewed": false
  },
  "generation_metadata": {
    "base_template_used": "template_style_2",
    "variation_strategy": "parameter_substitution",
    "semantic_smoother_passes": 1,
    "ood_contamination": false
  },
  "metadata": {
    "generated_at": "2025-08-04T18:31:13.611290",
    "fee_tier": "mid",
    "num_deliverables": 1,
    "campaign_type": "New Season",
    "product_category": "Automotive"
  }
}