{
  "sample_id": "sample_1691",
  "chunk_id": "sample_1691_c1",
  "text": "Brooklyn Edwards for Bed Bath N' Table - $9,175 budget\n            Need: 1 x Instagram story\n            11w exclusivity, 3m engagement\n            Usage rights: 7 months\n            Start: September 2025\n\nAdditional notes: TBC on exact dates, around $9,175 budget",
  "token_count": 58,
  "labels": [
    "brand",
    "campaign",
    "client",
    "deliverables",
    "engagement_term",
    "fee",
    "usage_term"
  ]
}