{
  "sample_id": "sample_2358",
  "chunk_id": "sample_2358_c1",
  "text": "Brandon Nelson for JB Hi-Fi - $14,976 budget\n            Need: 3 x Meet and greet, 2 x Article contribution, 3 x Instagram reel, 3 x Instagram story, 2 x 30-second Instagram reel\n            11w exclusivity, 5m engagement\n            Usage rights: 7 months\n            Start: October 2025\n\nAdditional notes: TBC on exact dates, around $14,976 budget",
  "token_count": 86,
  "labels": [
    "brand",
    "client",
    "deliverables",
    "engagement_term",
    "fee",
    "usage_term"
  ]
}