{
  "sample_id": "sample_3694",
  "chunk_id": "sample_3694_c1",
  "text": "Hey team, looking to work with Blake Cox for Priceline. Budget is approx $29,272 - need 1 x 30-second Instagram reel, 2 x Instagram story, 2 x Brand ambassador content. 10 weeks exclusivity, 4 month engagement. Usage: 10 months. Start date: September 2025.",
  "token_count": 68,
  "labels": [
    "brand",
    "campaign",
    "client",
    "deliverables",
    "engagement_term",
    "exclusivity_period",
    "fee",
    "usage_term"
  ]
}