{
  "sample_id": "sample_986",
  "generation_timestamp": "2025-08-04T18:30:05.104449",
  "generator_version": "v1.0",
  "batch_id": "batch_010",
  "classification": {
    "document_type": "INFLUENCER_AGREEMENT",
    "confidence_target": 0.85,
    "complexity_level": "simple",
    "industry": "home",
    "should_process": true
  },
  "raw_input": {
    "text": "• Influencer: Isabella Garcia\n            • Brand: IKEA\n            • Fee: ~$20,277\n            • Deliverables: 1 x LinkedIn post\n            • Exclusivity: 2 weeks\n            • Engagement: 6 months\n            • Usage: 6 months\n            • Start: January 2026",
    "token_count": 65,
    "requires_chunking": false,
    "text_style": "bullet_points",
    "completeness": "complete"
  },
  "extracted_fields": {
    "influencer": "Isabella Garcia",
    "client": "IKEA",
    "brand": "IKEA",
    "campaign": "IKEA Campaign",
    "fee": "$20,277",
    "fee_numeric": 20277,
    "deliverables": [
      "1 x LinkedIn post"
    ],
    "exclusivity_period": "2 weeks",
    "exclusivity_scope": "similar",
    "engagement_term": "6 months",
    "usage_term": "6 months",
    "territory": "Australia",
    "start_date": "January 2026"
  },
  "template_mapping": {
    "best_template_match": "template_style_2",
    "match_confidence": 0.9,
    "fallback_templates": [
      "template_01",
      "template_02"
    ]
  },
  "validation_scores": {
    "semantic_coherence": 0.7411523801136657,
    "business_logic_valid": true,
    "temporal_logic_valid": true,
    "field_extractability": 0.8161618000366347,
    "human_reviewed": false
  },
  "generation_metadata": {
    "base_template_used": "template_style_2",
    "variation_strategy": "parameter_substitution",
    "semantic_smoother_passes": 1,
    "ood_contamination": false
  },
  "metadata": {
    "generated_at": "2025-08-04T18:30:05.088985",
    "fee_tier": "premium",
    "num_deliverables": 1,
    "campaign_type": "Collaboration",
    "product_category": "Travel & Tourism"
  }
}