{
  "sample_id": "sample_3807",
  "generation_timestamp": "2025-08-04T18:31:07.087991",
  "generator_version": "v1.0",
  "batch_id": "batch_039",
  "classification": {
    "document_type": "INFLUENCER_AGREEMENT",
    "confidence_target": 0.85,
    "complexity_level": "medium",
    "industry": "automotive",
    "should_process": true
  },
  "raw_input": {
    "text": "• Influencer: Reagan Rogers\n            • Brand: Supercheap Auto\n            • Fee: ~$2,899\n            • Deliverables: 1 x Meet and greet, 1 x LinkedIn post\n            • Exclusivity: 2 weeks\n            • Engagement: 6 months\n            • Usage: 12 months\n            • Start: January 2026\n\nNeed to confirm: deliverables",
    "token_count": 80,
    "requires_chunking": false,
    "text_style": "bullet_points",
    "completeness": "complete"
  },
  "extracted_fields": {
    "influencer": "Reagan Rogers",
    "client": "Supercheap Auto",
    "brand": "Supercheap Auto",
    "campaign": "Supercheap Auto Campaign",
    "fee": "$2,899",
    "fee_numeric": 2899,
    "deliverables": [
      "1 x Meet and greet",
      "1 x LinkedIn post"
    ],
    "exclusivity_period": "2 weeks",
    "exclusivity_scope": "similar",
    "engagement_term": "6 months",
    "usage_term": "12 months",
    "territory": "Australia",
    "start_date": "January 2026"
  },
  "template_mapping": {
    "best_template_match": "template_style_4",
    "match_confidence": 0.75,
    "fallback_templates": [
      "template_02",
      "template_03"
    ]
  },
  "validation_scores": {
    "semantic_coherence": 0.8730075292184241,
    "business_logic_valid": true,
    "temporal_logic_valid": true,
    "field_extractability": 0.9191695034314624,
    "human_reviewed": false
  },
  "generation_metadata": {
    "base_template_used": "template_style_4",
    "variation_strategy": "parameter_substitution",
    "semantic_smoother_passes": 1,
    "ood_contamination": false
  },
  "metadata": {
    "generated_at": "2025-08-04T18:31:07.073989",
    "fee_tier": "micro",
    "num_deliverables": 2,
    "campaign_type": "New Season",
    "product_category": "Food & Beverage"
  }
}