{
  "sample_id": "sample_2365",
  "generation_timestamp": "2025-08-04T18:30:36.616820",
  "generator_version": "v1.0",
  "batch_id": "batch_024",
  "classification": {
    "document_type": "INFLUENCER_AGREEMENT",
    "confidence_target": 0.85,
    "complexity_level": "simple",
    "industry": "other",
    "should_process": true
  },
  "raw_input": {
    "text": "Need David Brown for Grill'd campaign. Budget around $4,744, looking for 1 x Twitter post, 3 x YouTube video, 3 x Twitter post, 3 x Instagram story. \n            12 week exclusivity from other similar brands. \n            Campaign runs January 2026. Usage rights for 6 months. \n            Engagement period: 3 months.",
    "token_count": 79,
    "requires_chunking": false,
    "text_style": "casual",
    "completeness": "complete"
  },
  "extracted_fields": {
    "influencer": "David Brown",
    "client": "Grill'd",
    "brand": "Grill'd",
    "campaign": "Grill'd Campaign",
    "fee": "$4,744",
    "fee_numeric": 4744,
    "deliverables": [
      "1 x Twitter post",
      "3 x YouTube video",
      "3 x Twitter post",
      "3 x Instagram story"
    ],
    "exclusivity_period": "12 weeks",
    "exclusivity_scope": "similar",
    "engagement_term": "3 months",
    "usage_term": "6 months",
    "territory": "Australia",
    "start_date": "January 2026"
  },
  "template_mapping": {
    "best_template_match": "template_style_2",
    "match_confidence": 0.85,
    "fallback_templates": [
      "template_01",
      "template_02"
    ]
  },
  "validation_scores": {
    "semantic_coherence": 0.9407066897355586,
    "business_logic_valid": true,
    "temporal_logic_valid": true,
    "field_extractability": 0.8141826495790956,
    "human_reviewed": false
  },
  "generation_metadata": {
    "base_template_used": "template_style_2",
    "variation_strategy": "parameter_substitution",
    "semantic_smoother_passes": 1,
    "ood_contamination": false
  },
  "metadata": {
    "generated_at": "2025-08-04T18:30:36.598819",
    "fee_tier": "micro",
    "num_deliverables": 4,
    "campaign_type": "Limited Edition",
    "product_category": "Technology & Electronics"
  }
}