{
  "batch_id": "batch_008",
  "generation_start": "2025-08-04T18:30:00.112454",
  "target_size": 100,
  "samples_generated": [
    {
      "sample_id": "sample_701",
      "filename": "sample_701_complex_food_inf.json",
      "classification": "INFLUENCER_AGREEMENT",
      "complexity": "complex",
      "industry": "food"
    },
    {
      "sample_id": "sample_702",
      "filename": "sample_702_simple_other_inf.json",
      "classification": "INFLUENCER_AGREEMENT",
      "complexity": "simple",
      "industry": "other"
    },
    {
      "sample_id": "sample_703",
      "filename": "sample_703_simple_tech_inf.json",
      "classification": "INFLUENCER_AGREEMENT",
      "complexity": "simple",
      "industry": "tech"
    },
    {
      "sample_id": "sample_704",
      "filename": "sample_704_simple_food_inf.json",
      "classification": "INFLUENCER_AGREEMENT",
      "complexity": "simple",
      "industry": "food"
    },
    {
      "sample_id": "sample_705",
      "filename": "sample_705_simple_automotive_inf.json",
      "classification": "INFLUENCER_AGREEMENT",
      "complexity": "simple",
      "industry": "automotive"
    },
    {
      "sample_id": "sample_706",
      "filename": "sample_706_simple_other_inf.json",
      "classification": "INFLUENCER_AGREEMENT",
      "complexity": "simple",
      "industry": "other"
    },
    {
      "sample_id": "sample_707",
      "filename": "sample_707_complex_fashion_inf.json",
      "classification": "INFLUENCER_AGREEMENT",
      "complexity": "complex",
      "industry": "fashion"
    },
    {
      "sample_id": "sample_708",
      "filename": "sample_708_simple_tech_inf.json",
      "classification": "INFLUENCER_AGREEMENT",
      "complexity": "simple",
      "industry": "tech"
    },
    {
      "sample_id": "sample_709",
      "filename": "sample_709_simple_home_inf.json",
      "classification": "INFLUENCER_AGREEMENT",
      "complexity": "simple",
      "industry": "home"
    },
    {
      "sample_id": "sample_710",
      "filename": "sample_710_simple_tech_inf.json",
      "classification": "INFLUENCER_AGREEMENT",
      "complexity": "simple",
      "industry": "tech"
    },
    {
      "sample_id": "sample_711",
      "filename": "sample_711_simple_other_inf.json",
      "classification": "INFLUENCER_AGREEMENT",
      "complexity": "simple",
      "industry": "other"
    },
    {
      "sample_id": "sample_712",
      "filename": "sample_712_simple_other_inf.json",
      "classification": "INFLUENCER_AGREEMENT",
      "complexity": "simple",
      "industry": "other"
    },
    {
      "sample_id": "sample_713",
      "filename": "sample_713_medium_other_inf.json",
      "classification": "INFLUENCER_AGREEMENT",
      "complexity": "medium",
      "industry": "other"
    },
    {
      "sample_id": "sample_714",
      "filename": "sample_714_complex_food_inf.json",
      "classification": "INFLUENCER_AGREEMENT",
      "complexity": "complex",
      "industry": "food"
    },
    {
      "sample_id": "sample_715",
      "filename": "sample_715_simple_food_inf.json",
      "classification": "INFLUENCER_AGREEMENT",
      "complexity": "simple",
      "industry": "food"
    },
    {
      "sample_id": "sample_716",
      "filename": "sample_716_medium_other_inf.json",
      "classification": "INFLUENCER_AGREEMENT",
      "complexity": "medium",
      "industry": "other"
    },
    {
      "sample_id": "sample_717",
      "filename": "sample_717_simple_automotive_inf.json",
      "classification": "INFLUENCER_AGREEMENT",
      "complexity": "simple",
      "industry": "automotive"
    },
    {
      "sample_id": "sample_718",
      "filename": "sample_718_medium_other_inf.json",
      "classification": "INFLUENCER_AGREEMENT",
      "complexity": "medium",
      "industry": "other"
    },
    {
      "sample_id": "sample_719",
      "filename": "sample_719_medium_automotive_inf.json",
      "classification": "INFLUENCER_AGREEMENT",
      "complexity": "medium",
      "industry": "automotive"
    },
    {
      "sample_id": "sample_720",
      "filename": "sample_720_simple_home_inf.json",
      "classification": "INFLUENCER_AGREEMENT",
      "complexity": "simple",
      "industry": "home"
    },
    {
      "sample_id": "sample_721",
      "filename": "sample_721_simple_other_inf.json",
      "classification": "INFLUENCER_AGREEMENT",
      "complexity": "simple",
      "industry": "other"
    },
    {
      "sample_id": "sample_722",
      "filename": "sample_722_medium_tech_inf.json",
      "classification": "INFLUENCER_AGREEMENT",
      "complexity": "medium",
      "industry": "tech"
    },
    {
      "sample_id": "sample_723",
      "filename": "sample_723_medium_tech_inf.json",
      "classification": "INFLUENCER_AGREEMENT",
      "complexity": "medium",
      "industry": "tech"
    },
    {
      "sample_id": "sample_724",
      "filename": "sample_724_simple_other_inf.json",
      "classification": "INFLUENCER_AGREEMENT",
      "complexity": "simple",
      "industry": "other"
    },
    {
      "sample_id": "sample_725",
      "filename": "sample_725_complex_beauty_inf.json",
      "classification": "INFLUENCER_AGREEMENT",
      "complexity": "complex",
      "industry": "beauty"
    },
    {
      "sample_id": "sample_726",
      "filename": "sample_726_simple_home_inf.json",
      "classification": "INFLUENCER_AGREEMENT",
      "complexity": "simple",
      "industry": "home"
    },
    {
      "sample_id": "sample_727",
      "filename": "sample_727_simple_other_inf.json",
      "classification": "INFLUENCER_AGREEMENT",
      "complexity": "simple",
      "industry": "other"
    },
    {
      "sample_id": "sample_728",
      "filename": "sample_728_medium_fashion_inf.json",
      "classification": "INFLUENCER_AGREEMENT",
      "complexity": "medium",
      "industry": "fashion"
    },
    {
      "sample_id": "sample_729",
      "filename": "sample_729_simple_fashion_inf.json",
      "classification": "INFLUENCER_AGREEMENT",
      "complexity": "simple",
      "industry": "fashion"
    },
    {
      "sample_id": "sample_730",
      "filename": "sample_730_medium_other_inf.json",
      "classification": "INFLUENCER_AGREEMENT",
      "complexity": "medium",
      "industry": "other"
    },
    {
      "sample_id": "sample_731",
      "filename": "sample_731_complex_other_inf.json",
      "classification": "INFLUENCER_AGREEMENT",
      "complexity": "complex",
      "industry": "other"
    },
    {
      "sample_id": "sample_732",
      "filename": "sample_732_simple_other_inf.json",
      "classification": "INFLUENCER_AGREEMENT",
      "complexity": "simple",
      "industry": "other"
    },
    {
      "sample_id": "sample_733",
      "filename": "sample_733_simple_other_inf.json",
      "classification": "INFLUENCER_AGREEMENT",
      "complexity": "simple",
      "industry": "other"
    },
    {
      "sample_id": "sample_734",
      "filename": "sample_734_simple_fashion_inf.json",
      "classification": "INFLUENCER_AGREEMENT",
      "complexity": "simple",
      "industry": "fashion"
    },
    {
      "sample_id": "sample_735",
      "filename": "sample_735_simple_tech_inf.json",
      "classification": "INFLUENCER_AGREEMENT",
      "complexity": "simple",
      "industry": "tech"
    },
    {
      "sample_id": "sample_736",
      "filename": "sample_736_medium_fashion_inf.json",
      "classification": "INFLUENCER_AGREEMENT",
      "complexity": "medium",
      "industry": "fashion"
    },
    {
      "sample_id": "sample_737",
      "filename": "sample_737_medium_other_inf.json",
      "classification": "INFLUENCER_AGREEMENT",
      "complexity": "medium",
      "industry": "other"
    },
    {
      "sample_id": "sample_738",
      "filename": "sample_738_simple_food_inf.json",
      "classification": "INFLUENCER_AGREEMENT",
      "complexity": "simple",
      "industry": "food"
    },
    {
      "sample_id": "sample_739",
      "filename": "sample_739_medium_food_inf.json",
      "classification": "INFLUENCER_AGREEMENT",
      "complexity": "medium",
      "industry": "food"
    },
    {
      "sample_id": "sample_740",
      "filename": "sample_740_complex_other_inf.json",
      "classification": "INFLUENCER_AGREEMENT",
      "complexity": "complex",
      "industry": "other"
    },
    {
      "sample_id": "sample_741",
      "filename": "sample_741_simple_food_inf.json",
      "classification": "INFLUENCER_AGREEMENT",
      "complexity": "simple",
      "industry": "food"
    },
    {
      "sample_id": "sample_742",
      "filename": "sample_742_complex_other_inf.json",
      "classification": "INFLUENCER_AGREEMENT",
      "complexity": "complex",
      "industry": "other"
    },
    {
      "sample_id": "sample_743",
      "filename": "sample_743_simple_other_inf.json",
      "classification": "INFLUENCER_AGREEMENT",
      "complexity": "simple",
      "industry": "other"
    },
    {
      "sample_id": "sample_744",
      "filename": "sample_744_complex_tech_inf.json",
      "classification": "INFLUENCER_AGREEMENT",
      "complexity": "complex",
      "industry": "tech"
    },
    {
      "sample_id": "sample_745",
      "filename": "sample_745_simple_beauty_inf.json",
      "classification": "INFLUENCER_AGREEMENT",
      "complexity": "simple",
      "industry": "beauty"
    },
    {
      "sample_id": "sample_746",
      "filename": "sample_746_simple_food_inf.json",
      "classification": "INFLUENCER_AGREEMENT",
      "complexity": "simple",
      "industry": "food"
    },
    {
      "sample_id": "sample_747",
      "filename": "sample_747_complex_food_inf.json",
      "classification": "INFLUENCER_AGREEMENT",
      "complexity": "complex",
      "industry": "food"
    },
    {
      "sample_id": "sample_748",
      "filename": "sample_748_simple_food_inf.json",
      "classification": "INFLUENCER_AGREEMENT",
      "complexity": "simple",
      "industry": "food"
    },
    {
      "sample_id": "sample_749",
      "filename": "sample_749_complex_automotive_inf.json",
      "classification": "INFLUENCER_AGREEMENT",
      "complexity": "complex",
      "industry": "automotive"
    },
    {
      "sample_id": "sample_750",
      "filename": "sample_750_complex_beauty_inf.json",
      "classification": "INFLUENCER_AGREEMENT",
      "complexity": "complex",
      "industry": "beauty"
    },
    {
      "sample_id": "sample_751",
      "filename": "sample_751_simple_beauty_inf.json",
      "classification": "INFLUENCER_AGREEMENT",
      "complexity": "simple",
      "industry": "beauty"
    },
    {
      "sample_id": "sample_752",
      "filename": "sample_752_complex_food_inf.json",
      "classification": "INFLUENCER_AGREEMENT",
      "complexity": "complex",
      "industry": "food"
    },
    {
      "sample_id": "sample_753",
      "filename": "sample_753_simple_beauty_inf.json",
      "classification": "INFLUENCER_AGREEMENT",
      "complexity": "simple",
      "industry": "beauty"
    },
    {
      "sample_id": "sample_754",
      "filename": "sample_754_simple_beauty_inf.json",
      "classification": "INFLUENCER_AGREEMENT",
      "complexity": "simple",
      "industry": "beauty"
    },
    {
      "sample_id": "sample_755",
      "filename": "sample_755_complex_other_inf.json",
      "classification": "INFLUENCER_AGREEMENT",
      "complexity": "complex",
      "industry": "other"
    },
    {
      "sample_id": "sample_756",
      "filename": "sample_756_simple_fashion_inf.json",
      "classification": "INFLUENCER_AGREEMENT",
      "complexity": "simple",
      "industry": "fashion"
    },
    {
      "sample_id": "sample_757",
      "filename": "sample_757_complex_food_inf.json",
      "classification": "INFLUENCER_AGREEMENT",
      "complexity": "complex",
      "industry": "food"
    },
    {
      "sample_id": "sample_758",
      "filename": "sample_758_simple_other_inf.json",
      "classification": "INFLUENCER_AGREEMENT",
      "complexity": "simple",
      "industry": "other"
    },
    {
      "sample_id": "sample_759",
      "filename": "sample_759_medium_tech_inf.json",
      "classification": "INFLUENCER_AGREEMENT",
      "complexity": "medium",
      "industry": "tech"
    },
    {
      "sample_id": "sample_760",
      "filename": "sample_760_simple_other_inf.json",
      "classification": "INFLUENCER_AGREEMENT",
      "complexity": "simple",
      "industry": "other"
    },
    {
      "sample_id": "sample_761",
      "filename": "sample_761_simple_food_inf.json",
      "classification": "INFLUENCER_AGREEMENT",
      "complexity": "simple",
      "industry": "food"
    },
    {
      "sample_id": "sample_762",
      "filename": "sample_762_medium_tech_inf.json",
      "classification": "INFLUENCER_AGREEMENT",
      "complexity": "medium",
      "industry": "tech"
    },
    {
      "sample_id": "sample_763",
      "filename": "sample_763_simple_food_inf.json",
      "classification": "INFLUENCER_AGREEMENT",
      "complexity": "simple",
      "industry": "food"
    },
    {
      "sample_id": "sample_764",
      "filename": "sample_764_simple_other_inf.json",
      "classification": "INFLUENCER_AGREEMENT",
      "complexity": "simple",
      "industry": "other"
    },
    {
      "sample_id": "sample_765",
      "filename": "sample_765_simple_automotive_inf.json",
      "classification": "INFLUENCER_AGREEMENT",
      "complexity": "simple",
      "industry": "automotive"
    },
    {
      "sample_id": "sample_766",
      "filename": "sample_766_medium_other_inf.json",
      "classification": "INFLUENCER_AGREEMENT",
      "complexity": "medium",
      "industry": "other"
    },
    {
      "sample_id": "sample_767",
      "filename": "sample_767_complex_home_inf.json",
      "classification": "INFLUENCER_AGREEMENT",
      "complexity": "complex",
      "industry": "home"
    },
    {
      "sample_id": "sample_768",
      "filename": "sample_768_simple_food_inf.json",
      "classification": "INFLUENCER_AGREEMENT",
      "complexity": "simple",
      "industry": "food"
    },
    {
      "sample_id": "sample_769",
      "filename": "sample_769_complex_other_inf.json",
      "classification": "INFLUENCER_AGREEMENT",
      "complexity": "complex",
      "industry": "other"
    },
    {
      "sample_id": "sample_770",
      "filename": "sample_770_simple_food_inf.json",
      "classification": "INFLUENCER_AGREEMENT",
      "complexity": "simple",
      "industry": "food"
    },
    {
      "sample_id": "sample_771",
      "filename": "sample_771_medium_other_inf.json",
      "classification": "INFLUENCER_AGREEMENT",
      "complexity": "medium",
      "industry": "other"
    },
    {
      "sample_id": "sample_772",
      "filename": "sample_772_simple_other_inf.json",
      "classification": "INFLUENCER_AGREEMENT",
      "complexity": "simple",
      "industry": "other"
    },
    {
      "sample_id": "sample_773",
      "filename": "sample_773_simple_other_inf.json",
      "classification": "INFLUENCER_AGREEMENT",
      "complexity": "simple",
      "industry": "other"
    },
    {
      "sample_id": "sample_774",
      "filename": "sample_774_medium_fashion_inf.json",
      "classification": "INFLUENCER_AGREEMENT",
      "complexity": "medium",
      "industry": "fashion"
    },
    {
      "sample_id": "sample_775",
      "filename": "sample_775_simple_food_inf.json",
      "classification": "INFLUENCER_AGREEMENT",
      "complexity": "simple",
      "industry": "food"
    },
    {
      "sample_id": "sample_776",
      "filename": "sample_776_medium_food_inf.json",
      "classification": "INFLUENCER_AGREEMENT",
      "complexity": "medium",
      "industry": "food"
    },
    {
      "sample_id": "sample_777",
      "filename": "sample_777_complex_tech_inf.json",
      "classification": "INFLUENCER_AGREEMENT",
      "complexity": "complex",
      "industry": "tech"
    },
    {
      "sample_id": "sample_778",
      "filename": "sample_778_simple_fashion_inf.json",
      "classification": "INFLUENCER_AGREEMENT",
      "complexity": "simple",
      "industry": "fashion"
    },
    {
      "sample_id": "sample_779",
      "filename": "sample_779_simple_other_inf.json",
      "classification": "INFLUENCER_AGREEMENT",
      "complexity": "simple",
      "industry": "other"
    },
    {
      "sample_id": "sample_780",
      "filename": "sample_780_simple_other_inf.json",
      "classification": "INFLUENCER_AGREEMENT",
      "complexity": "simple",
      "industry": "other"
    },
    {
      "sample_id": "sample_781",
      "filename": "sample_781_medium_beauty_inf.json",
      "classification": "INFLUENCER_AGREEMENT",
      "complexity": "medium",
      "industry": "beauty"
    },
    {
      "sample_id": "sample_782",
      "filename": "sample_782_simple_other_inf.json",
      "classification": "INFLUENCER_AGREEMENT",
      "complexity": "simple",
      "industry": "other"
    },
    {
      "sample_id": "sample_783",
      "filename": "sample_783_simple_fashion_inf.json",
      "classification": "INFLUENCER_AGREEMENT",
      "complexity": "simple",
      "industry": "fashion"
    },
    {
      "sample_id": "sample_784",
      "filename": "sample_784_simple_food_inf.json",
      "classification": "INFLUENCER_AGREEMENT",
      "complexity": "simple",
      "industry": "food"
    },
    {
      "sample_id": "sample_785",
      "filename": "sample_785_medium_other_inf.json",
      "classification": "INFLUENCER_AGREEMENT",
      "complexity": "medium",
      "industry": "other"
    },
    {
      "sample_id": "sample_786",
      "filename": "sample_786_medium_home_inf.json",
      "classification": "INFLUENCER_AGREEMENT",
      "complexity": "medium",
      "industry": "home"
    },
    {
      "sample_id": "sample_787",
      "filename": "sample_787_medium_food_inf.json",
      "classification": "INFLUENCER_AGREEMENT",
      "complexity": "medium",
      "industry": "food"
    },
    {
      "sample_id": "sample_788",
      "filename": "sample_788_medium_other_inf.json",
      "classification": "INFLUENCER_AGREEMENT",
      "complexity": "medium",
      "industry": "other"
    },
    {
      "sample_id": "sample_789",
      "filename": "sample_789_medium_other_inf.json",
      "classification": "INFLUENCER_AGREEMENT",
      "complexity": "medium",
      "industry": "other"
    },
    {
      "sample_id": "sample_790",
      "filename": "sample_790_medium_other_inf.json",
      "classification": "INFLUENCER_AGREEMENT",
      "complexity": "medium",
      "industry": "other"
    },
    {
      "sample_id": "sample_791",
      "filename": "sample_791_simple_beauty_inf.json",
      "classification": "INFLUENCER_AGREEMENT",
      "complexity": "simple",
      "industry": "beauty"
    },
    {
      "sample_id": "sample_792",
      "filename": "sample_792_medium_beauty_inf.json",
      "classification": "INFLUENCER_AGREEMENT",
      "complexity": "medium",
      "industry": "beauty"
    },
    {
      "sample_id": "sample_793",
      "filename": "sample_793_simple_other_inf.json",
      "classification": "INFLUENCER_AGREEMENT",
      "complexity": "simple",
      "industry": "other"
    },
    {
      "sample_id": "sample_794",
      "filename": "sample_794_simple_beauty_inf.json",
      "classification": "INFLUENCER_AGREEMENT",
      "complexity": "simple",
      "industry": "beauty"
    },
    {
      "sample_id": "sample_795",
      "filename": "sample_795_complex_other_inf.json",
      "classification": "INFLUENCER_AGREEMENT",
      "complexity": "complex",
      "industry": "other"
    },
    {
      "sample_id": "sample_796",
      "filename": "sample_796_medium_tech_inf.json",
      "classification": "INFLUENCER_AGREEMENT",
      "complexity": "medium",
      "industry": "tech"
    },
    {
      "sample_id": "sample_797",
      "filename": "sample_797_complex_tech_inf.json",
      "classification": "INFLUENCER_AGREEMENT",
      "complexity": "complex",
      "industry": "tech"
    },
    {
      "sample_id": "sample_798",
      "filename": "sample_798_simple_other_inf.json",
      "classification": "INFLUENCER_AGREEMENT",
      "complexity": "simple",
      "industry": "other"
    },
    {
      "sample_id": "sample_799",
      "filename": "sample_799_simple_fashion_inf.json",
      "classification": "INFLUENCER_AGREEMENT",
      "complexity": "simple",
      "industry": "fashion"
    },
    {
      "sample_id": "sample_800",
      "filename": "sample_800_medium_other_inf.json",
      "classification": "INFLUENCER_AGREEMENT",
      "complexity": "medium",
      "industry": "other"
    }
  ],
  "generation_end": "2025-08-04T18:30:01.228103",
  "quality_metrics": {
    "total_samples": 100,
    "classification_distribution": {
      "INFLUENCER_AGREEMENT": 100
    },
    "complexity_distribution": {
      "complex": 19,
      "simple": 54,
      "medium": 27
    },
    "industry_distribution": {
      "food": 20,
      "other": 38,
      "tech": 12,
      "automotive": 5,
      "fashion": 10,
      "home": 5,
      "beauty": 10
    },
    "average_validation_score": 0.8085729154063697
  }
}